pokemontcgsdkasync/__init__.py
pokemontcgsdkasync/ability.py
pokemontcgsdkasync/ancienttrait.py
pokemontcgsdkasync/asyncclientcontext.py
pokemontcgsdkasync/attack.py
pokemontcgsdkasync/card.py
pokemontcgsdkasync/cardimage.py
pokemontcgsdkasync/cardmarket.py
pokemontcgsdkasync/config.py
pokemontcgsdkasync/legality.py
pokemontcgsdkasync/pokemontcgexception.py
pokemontcgsdkasync/query.py
pokemontcgsdkasync/querybuilder.py
pokemontcgsdkasync/rarity.py
pokemontcgsdkasync/resistance.py
pokemontcgsdkasync/set.py
pokemontcgsdkasync/setimage.py
pokemontcgsdkasync/subtype.py
pokemontcgsdkasync/supertype.py
pokemontcgsdkasync/tcgplayer.py
pokemontcgsdkasync/type.py
pokemontcgsdkasync/weakness.py
tests/__init__.py
tests/test_card.py
tests/test_config.py
tests/test_pokemontcgexception.py
tests/test_set.py
tests/test_subtype.py
tests/test_supertype.py
tests/test_type.py
pokemontcgsdkasync-0.2.0.dist-info/LICENSE.txt
pokemontcgsdkasync-0.2.0.dist-info/METADATA
pokemontcgsdkasync-0.2.0.dist-info/WHEEL
pokemontcgsdkasync-0.2.0.dist-info/top_level.txt
pokemontcgsdkasync-0.2.0.dist-info/RECORD
