Metadata-Version: 2.1
Name: pokemontcgsdkasync
Version: 0.2.0
Summary: Pokemon TCG SDK for pokemontcg.io using asyncio
Home-page: https://github.com/Pole458/pokemon-tcg-sdk-python-async
Author: Paolo D'Alessandro
Author-email: pole.gamedev@gmail.com
License: MIT
Download-URL: https://github.com/Pole458/pokemon-tcg-sdk-python-async/tarball/0.2.0
Keywords: pokemon tcg sdk trading card game api rest async
Platform: UNKNOWN
Classifier: Development Status :: 5 - Production/Stable
Classifier: Intended Audience :: Developers
Classifier: License :: OSI Approved :: MIT License
Classifier: Natural Language :: English
Classifier: Programming Language :: Python :: 3
Classifier: Operating System :: OS Independent
Requires-Python: >=3.6
License-File: LICENSE.txt
Requires-Dist: dacite (<2.0.0,>=1.6.0)
Requires-Dist: aiohttp (<4.0.0,>=3.8.1)
Provides-Extra: tests
Requires-Dist: mock ; extra == 'tests'
Requires-Dist: nose ; extra == 'tests'
Requires-Dist: coverage ; extra == 'tests'
Requires-Dist: yanc ; extra == 'tests'
Requires-Dist: preggy ; extra == 'tests'
Requires-Dist: tox ; extra == 'tests'
Requires-Dist: ipdb ; extra == 'tests'
Requires-Dist: coveralls ; extra == 'tests'
Requires-Dist: sphinx ; extra == 'tests'
